Topsis/__init__.py
Topsis/__main__.py
Topsis_Loveneet_102116111-0.0.0.dist-info/LICENSE
Topsis_Loveneet_102116111-0.0.0.dist-info/METADATA
Topsis_Loveneet_102116111-0.0.0.dist-info/WHEEL
Topsis_Loveneet_102116111-0.0.0.dist-info/entry_points.txt
Topsis_Loveneet_102116111-0.0.0.dist-info/top_level.txt
Topsis_Loveneet_102116111-0.0.0.dist-info/RECORD
