Metadata-Version: 2.1
Name: Topsis-Loveneet-102116111
Version: 0.0.0
Summary: TOPSIS implementation by Loveneet Kaur
Home-page: https://github.com/kaurneetlove/Topsis-Loveneet-102116111
Author: Loveneet Kaur
Author-email: kaurneetlove@gmail.com
License: MIT
Classifier: License :: OSI Approved :: MIT License
Classifier: Programming Language :: Python :: 3.6
Classifier: Programming Language :: Python :: 3.7
Classifier: Programming Language :: Python :: 3.8
License-File: LICENSE
Requires-Dist: numpy
Requires-Dist: pandas
Requires-Dist: sys
